MANIFEST.in
README.md
setup.py
django_locking_south.egg-info/PKG-INFO
django_locking_south.egg-info/SOURCES.txt
django_locking_south.egg-info/dependency_links.txt
django_locking_south.egg-info/not-zip-safe
django_locking_south.egg-info/requires.txt
django_locking_south.egg-info/top_level.txt
locking_south/__init__.py
locking_south/management/__init__.py
locking_south/management/commands/__init__.py
locking_south/management/commands/safe_migrate.py