Metadata-Version: 1.0
Name: django-locking-south
Version: 0.1.0
Summary: Prevent South from running concurrently
Home-page: https://github.com/mattrobenolt/django-locking-south
Author: Matt Robenolt
Author-email: matt@ydekproductions.com
License: MIT
Platform: UNKNOWN
Classifier: Development Status :: 4 - Beta
Classifier: Intended Audience :: Developers
Classifier: Intended Audience :: System Administrators
Classifier: Operating System :: OS Independent
Classifier: Programming Language :: Python
Classifier: Topic :: Software Development :: Libraries :: Python Modules
